pusimp/__init__.py
pusimp/prevent_user_site_imports.py
pusimp/py.typed
pusimp/utils.py
pusimp-0.1.1.dist-info/AUTHORS
pusimp-0.1.1.dist-info/LICENSE
pusimp-0.1.1.dist-info/METADATA
pusimp-0.1.1.dist-info/WHEEL
pusimp-0.1.1.dist-info/top_level.txt
pusimp-0.1.1.dist-info/RECORD
