Metadata-Version: 2.1
Name: pusimp
Version: 0.1.1
Summary: Prevent user-site imports
Author-email: Francesco Ballarin <francesco.ballarin@unicatt.it>, Drew Parsons <dparsons@debian.org>
Maintainer-email: Francesco Ballarin <francesco.ballarin@unicatt.it>, Drew Parsons <dparsons@debian.org>
License: Copyright 2023-2024 pusimp authors and contributors
Project-URL: repository, https://github.com/python-pusimp/pusimp
Project-URL: issues, https://github.com/python-pusimp/pusimp/issues
Classifier: Development Status :: 3 - Alpha
Classifier: Intended Audience :: Developers
Classifier: Intended Audience :: Science/Research
Classifier: License :: OSI Approved :: MIT License
Classifier: Operating System :: POSIX
Classifier: Operating System :: POSIX :: Linux
Classifier: Operating System :: MacOS :: MacOS X
Classifier: Programming Language :: Python
Classifier: Programming Language :: Python :: 3
Classifier: Programming Language :: Python :: 3.8
Classifier: Programming Language :: Python :: 3.9
Classifier: Programming Language :: Python :: 3.10
Classifier: Programming Language :: Python :: 3.11
Classifier: Programming Language :: Python :: 3.12
Classifier: Topic :: Software Development :: Libraries :: Python Modules
Requires-Python: >=3.8
License-File: LICENSE
License-File: AUTHORS
Provides-Extra: lint
Requires-Dist: isort ; extra == 'lint'
Requires-Dist: mypy ; extra == 'lint'
Requires-Dist: ruff ; extra == 'lint'
Requires-Dist: yamllint ; extra == 'lint'
Provides-Extra: tests
Requires-Dist: coverage[toml] ; extra == 'tests'
Requires-Dist: pip ; extra == 'tests'
Requires-Dist: pytest ; extra == 'tests'
Requires-Dist: virtualenv ; extra == 'tests'
